sparweltbitool/redshift.py
sparweltbitool/client_s3.py
sparweltbitool/execution_time.py
sparweltbitool/validation.py
sparweltbitool/singleton.py
sparweltbitool/client_emarsys.py
sparweltbitool/client_redis.py
sparweltbitool/config.py
sparweltbitool/logger.py
sparweltbitool/s3.py
sparweltbitool/__init__.py
sparweltbitool-0.1.8.dist-info/pbr.json
sparweltbitool-0.1.8.dist-info/metadata.json
sparweltbitool-0.1.8.dist-info/top_level.txt
sparweltbitool-0.1.8.dist-info/METADATA
sparweltbitool-0.1.8.dist-info/DESCRIPTION.rst
sparweltbitool-0.1.8.dist-info/RECORD
sparweltbitool-0.1.8.dist-info/WHEEL
