Metadata-Version: 2.0
Name: sparweltbitool
Version: 0.1.8
Summary: Standard modules used by Sparwelt GmbH BI Team in Web Services
Home-page: https://github.com/sparwelt/bitool.git
Author: Paweł Graczyk
Author-email: abs-saas@sparwelt.de
License: MIT
Platform: UNKNOWN
Classifier: Development Status :: 5 - Production/Stable
Classifier: Intended Audience :: Developers
Classifier: Natural Language :: English
Classifier: License :: OSI Approved :: MIT License
Classifier: Operating System :: OS Independent
Classifier: Programming Language :: Python :: 3.4
Classifier: Topic :: Software Development :: Libraries :: Python Modules
